Metadata-Version: 2.4
Name: iflow-mcp_mcp_server_bing
Version: 0.1.1
Summary: MCP server implementation for Bing Search API integration
Author-email: Hanchung Lee <leehanchung@gmail.com>
License-Expression: MIT
License-File: LICENSE
Requires-Python: >=3.10
Requires-Dist: httpx>=0.28.1
Requires-Dist: mcp[cli]>=1.4.1
Requires-Dist: python-dotenv>=1.0.1
Provides-Extra: dev
Requires-Dist: mypy>=1.9.0; extra == 'dev'
Requires-Dist: pyright>=1.1.398; extra == 'dev'
Requires-Dist: pytest-asyncio>=0.23.5; extra == 'dev'
Requires-Dist: pytest-cov>=4.1.0; extra == 'dev'
Requires-Dist: pytest>=8.0.0; extra == 'dev'
Requires-Dist: ruff>=0.11.0; extra == 'dev'
